underautomation/__init__.py
underautomation/staubli/__init__.py
underautomation/staubli/connection_parameters.py
underautomation/staubli/staubli_controller.py
underautomation/staubli/common/__init__.py
underautomation/staubli/common/soap_connect_parameters.py
underautomation/staubli/lib/UnderAutomation.Staubli.dll
underautomation/staubli/lib/version.txt
underautomation/staubli/license/__init__.py
underautomation/staubli/license/invalid_license_exception.py
underautomation/staubli/license/license_info.py
underautomation/staubli/license/license_state.py
underautomation/staubli/soap/__init__.py
underautomation/staubli/soap/soap_client.py
underautomation/staubli/soap/data/__init__.py
underautomation/staubli/soap/data/above_below_config.py
underautomation/staubli/soap/data/anthro_config.py
underautomation/staubli/soap/data/blend_type.py
underautomation/staubli/soap/data/cartesian_joint_position.py
underautomation/staubli/soap/data/cartesian_position.py
underautomation/staubli/soap/data/config.py
underautomation/staubli/soap/data/controller_task.py
underautomation/staubli/soap/data/controller_task_state.py
underautomation/staubli/soap/data/dh_parameters.py
underautomation/staubli/soap/data/diameter_axis3.py
underautomation/staubli/soap/data/frame.py
underautomation/staubli/soap/data/i_forward_kinematics.py
underautomation/staubli/soap/data/i_move_result.py
underautomation/staubli/soap/data/i_reverse_kinematics.py
underautomation/staubli/soap/data/joint_range.py
underautomation/staubli/soap/data/kinematic.py
underautomation/staubli/soap/data/length_axis3.py
underautomation/staubli/soap/data/motion_desc.py
underautomation/staubli/soap/data/motion_return_code.py
underautomation/staubli/soap/data/mount_type.py
underautomation/staubli/soap/data/move_type.py
underautomation/staubli/soap/data/parameter.py
underautomation/staubli/soap/data/physical_aio_attribute.py
underautomation/staubli/soap/data/physical_dio_attribute.py
underautomation/staubli/soap/data/physical_io.py
underautomation_staubli-0.1.1.0.dist-info/METADATA
underautomation_staubli-0.1.1.0.dist-info/WHEEL
underautomation_staubli-0.1.1.0.dist-info/top_level.txt
underautomation_staubli-0.1.1.0.dist-info/RECORD
