Metadata-Version: 2.4
Name: UnderAutomation.Staubli
Version: 0.1.1.0
Summary: Quickly create applications that communicate with your Staubli robots
Home-page: https://underautomation.com/staubli
Author: UnderAutomation
Author-email: support@underautomation.com
Project-URL: Documentation, https://underautomation.com/staubli/documentation/get-started-python
Project-URL: Source, https://github.com/underautomation/Staubli.py
Requires-Python: >=3.7
Requires-Dist: pythonnet==3.0.5
Dynamic: author
Dynamic: author-email
Dynamic: description
Dynamic: description-content-type
Dynamic: home-page
Dynamic: project-url
Dynamic: requires-dist
Dynamic: requires-python
Dynamic: summary
